README.md
setup.py
slydes/__init__.py
slydes/presentation.py
slydes/template.py
slydes.egg-info/PKG-INFO
slydes.egg-info/SOURCES.txt
slydes.egg-info/dependency_links.txt
slydes.egg-info/top_level.txt