Metadata-Version: 2.1
Name: slydes
Version: 0.0.2
Summary: Why not show your presentations with Python?
Home-page: https://github.com/jonatasbaldin/slydes
Author: Jonatas Baldin
Author-email: jonatas.baldin@gmail.com
License: MIT
Platform: UNKNOWN
Classifier: Development Status :: 3 - Alpha
Classifier: Environment :: Console
Classifier: Intended Audience :: Developers
Classifier: License :: OSI Approved :: MIT License
Classifier: Programming Language :: Python
Classifier: Topic :: Multimedia :: Graphics :: Presentation
